google/cloud/redis_cluster/__init__.py
google/cloud/redis_cluster/gapic_version.py
google/cloud/redis_cluster/py.typed
google/cloud/redis_cluster_v1/__init__.py
google/cloud/redis_cluster_v1/gapic_metadata.json
google/cloud/redis_cluster_v1/gapic_version.py
google/cloud/redis_cluster_v1/py.typed
google/cloud/redis_cluster_v1/services/__init__.py
google/cloud/redis_cluster_v1/services/cloud_redis_cluster/__init__.py
google/cloud/redis_cluster_v1/services/cloud_redis_cluster/async_client.py
google/cloud/redis_cluster_v1/services/cloud_redis_cluster/client.py
google/cloud/redis_cluster_v1/services/cloud_redis_cluster/pagers.py
google/cloud/redis_cluster_v1/services/cloud_redis_cluster/transports/__init__.py
google/cloud/redis_cluster_v1/services/cloud_redis_cluster/transports/base.py
google/cloud/redis_cluster_v1/services/cloud_redis_cluster/transports/grpc.py
google/cloud/redis_cluster_v1/services/cloud_redis_cluster/transports/grpc_asyncio.py
google/cloud/redis_cluster_v1/services/cloud_redis_cluster/transports/rest.py
google/cloud/redis_cluster_v1/services/cloud_redis_cluster/transports/rest_base.py
google/cloud/redis_cluster_v1/types/__init__.py
google/cloud/redis_cluster_v1/types/cloud_redis_cluster.py
google/cloud/redis_cluster_v1beta1/__init__.py
google/cloud/redis_cluster_v1beta1/gapic_metadata.json
google/cloud/redis_cluster_v1beta1/gapic_version.py
google/cloud/redis_cluster_v1beta1/py.typed
google/cloud/redis_cluster_v1beta1/services/__init__.py
google/cloud/redis_cluster_v1beta1/services/cloud_redis_cluster/__init__.py
google/cloud/redis_cluster_v1beta1/services/cloud_redis_cluster/async_client.py
google/cloud/redis_cluster_v1beta1/services/cloud_redis_cluster/client.py
google/cloud/redis_cluster_v1beta1/services/cloud_redis_cluster/pagers.py
google/cloud/redis_cluster_v1beta1/services/cloud_redis_cluster/transports/__init__.py
google/cloud/redis_cluster_v1beta1/services/cloud_redis_cluster/transports/base.py
google_cloud_redis_cluster-0.2.0.dist-info/licenses/LICENSE
google_cloud_redis_cluster-0.2.0.dist-info/METADATA
google_cloud_redis_cluster-0.2.0.dist-info/WHEEL
google_cloud_redis_cluster-0.2.0.dist-info/top_level.txt
google_cloud_redis_cluster-0.2.0.dist-info/RECORD
